{"files":[{"culture":"","installRoot":"","ngen":null,"path":"C:\\Users\\achuth\\Desktop\\Projects\\ConsoleWriteLineAnalyzer\\ConsoleWriteLineAnalyzer\\ConsoleWriteLineAnalyzer.CodeFixes\\bin\\Debug\\netstandard2.0\\ConsoleWriteLineAnalyzer.CodeFixes.dll","targetPath":"","vsixSubPath":""},{"culture":"","installRoot":"","ngen":null,"path":"C:\\Users\\achuth\\Desktop\\Projects\\ConsoleWriteLineAnalyzer\\ConsoleWriteLineAnalyzer\\ConsoleWriteLineAnalyzer\\bin\\Debug\\netstandard2.0\\ConsoleWriteLineAnalyzer.dll","targetPath":"","vsixSubPath":""}]}